odoo10_addon_subscription_action-10.0.1.0.0.99.dev2-py2.7-nspkg.pth
odoo/addons/subscription_action/README.rst
odoo/addons/subscription_action/__init__.py
odoo/addons/subscription_action/__manifest__.py
odoo/addons/subscription_action/i18n/subscription_action.pot
odoo/addons/subscription_action/models/__init__.py
odoo/addons/subscription_action/models/subscription_subscription.py
odoo/addons/subscription_action/static/description/icon.png
odoo/addons/subscription_action/tests/__init__.py
odoo/addons/subscription_action/tests/test_subscription_action.py
odoo/addons/subscription_action/views/subscription_subscription.xml
odoo10_addon_subscription_action-10.0.1.0.0.99.dev2.dist-info/METADATA
odoo10_addon_subscription_action-10.0.1.0.0.99.dev2.dist-info/RECORD
odoo10_addon_subscription_action-10.0.1.0.0.99.dev2.dist-info/WHEEL
odoo10_addon_subscription_action-10.0.1.0.0.99.dev2.dist-info/namespace_packages.txt
odoo10_addon_subscription_action-10.0.1.0.0.99.dev2.dist-info/top_level.txt
